noax/__init__.py
noax/layers/__init__.py
noax/layers/spectral_conv.py
noax-0.1.0.dist-info/METADATA
noax-0.1.0.dist-info/WHEEL
noax-0.1.0.dist-info/RECORD
